{
  "indexes": [
    {
      "collectionGroup": "dishes",
      "queryScope": "COLLECTION",
      "fields": [
        {
          "fieldPath": "sectionId",
          "order": "ASCENDING"
        },
        {
          "fieldPath": "order",
          "order": "ASCENDING"
        },
        {
          "fieldPath": "__name__",
          "order": "ASCENDING"
        }
      ]
    },
    {
      "collectionGroup": "orders",
      "queryScope": "COLLECTION",
      "fields": [
        {
          "fieldPath": "status",
          "order": "ASCENDING"
        },
        {
          "fieldPath": "createdAt",
          "order": "ASCENDING"
        }
      ]
    }
  ],
  "fieldOverrides": []
}
